coin_gecko/__init__.py
coin_gecko/coin.py
coin_gecko-1.1.1.dist-info/License.txt
coin_gecko-1.1.1.dist-info/METADATA
coin_gecko-1.1.1.dist-info/WHEEL
coin_gecko-1.1.1.dist-info/top_level.txt
coin_gecko-1.1.1.dist-info/RECORD
