Metadata-Version: 2.1
Name: coin-gecko
Version: 1.1.1
Summary: UNKNOWN
Home-page: UNKNOWN
Author: Arshi Khan
Author-email: arshi.khan67@gmail.com
License: MIT
Platform: UNKNOWN
Classifier: Programming Language :: Python :: 3
Classifier: License :: OSI Approved :: MIT License
Classifier: Operating System :: OS Independent
License-File: License.txt
